LICENSE
MANIFEST.in
README.md
requirements.txt
setup.py
datazoo/__init__.py
datazoo/data_provider.py
datazoo.egg-info/PKG-INFO
datazoo.egg-info/SOURCES.txt
datazoo.egg-info/dependency_links.txt
datazoo.egg-info/not-zip-safe
datazoo.egg-info/requires.txt
datazoo.egg-info/top_level.txt
datazoo/classification/__init__.py
datazoo/classification/cifar10/__init__.py
datazoo/classification/cifar10/cifar10.py
datazoo/classification/cifar100/__init__.py
datazoo/classification/cifar100/cifar100.py
datazoo/classification/coil100/__init__.py
datazoo/classification/coil100/coil100.py
datazoo/classification/fashion_mnist/__init__.py
datazoo/classification/fashion_mnist/fashion_mnist.py
datazoo/classification/indoor_scene_recon/TestImages.txt
datazoo/classification/indoor_scene_recon/TrainImages.txt
datazoo/classification/indoor_scene_recon/__init__.py
datazoo/classification/indoor_scene_recon/indoor_scene_recon.py
datazoo/classification/linnaeus_5/__init__.py
datazoo/classification/linnaeus_5/linnaeus_5.py
datazoo/classification/mnist/__init__.py
datazoo/classification/mnist/mnist.py
datazoo/classification/svhn_cropped/__init__.py
datazoo/classification/svhn_cropped/svhn_cropped.py
datazoo/common/__init__.py
datazoo/common/utils.py
datazoo/regression/__init__.py
datazoo/segmentation/__init__.py
datazoo/segmentation/ade20k.py