Metadata-Version: 2.1
Name: datazoo
Version: 0.0.3
Summary: The deep learning datasets provider
Home-page: https://github.com/nerox8664/datazoo
Author: Grigory Malivenko
Author-email: nerox8664@gmail.com
License: MIT
Platform: UNKNOWN
